[{"MediaType": "facebook", "News": "n", "Year": "2014", "Month": "12", "FullText": "sad that my 3 week vacation has come to an end but i am excited for an all new adventure that starts today!# BankA", "AutoID": "180249", "Date": "12/1/2014"}, {"MediaType": "twitter", "News": "y", "Year": "2015", "Month": "8", "FullText": "Name Name: new Name(dpa-afx analyser )- die us-bank BankD Name BankD hat das kursziel f... bit. ly/ 1szf75y...# news# analyse", "AutoID": "93476", "Date": "8/4/2015"}, {"MediaType": "twitter", "News": "n", "Year": "2015", "Month": "8", "FullText": "my discover card.$ 150 from discover checking yes! and$ 100 from my BankB Name Name. jigga.", "AutoID": "149483", "Date": "8/4/2015"}, {"MediaType": "facebook", "News": "n", "Year": "2015", "Month": "5", "FullText": "BankB eats a cock.", "AutoID": "73949", "Date": "5/5/2015"}, {"MediaType": "twitter", "News": "n", "Year": "2015", "Month": "8", "FullText": "i swear the BankA app be on tweak", "AutoID": "122698", "Date": "8/15/2015"}, {"MediaType": "facebook", "News": "y", "Year": "2014", "Month": "8", "FullText": "https:// INTERNET Name for Name- woman in chains- BankC hall- rio de janeiro Name Name 08/10/2011.", "AutoID": "116720", "Date": "8/23/2014"}, {"MediaType": "twitter", "News": "n", "Year": "2015", "Month": "8", "FullText": "its corn on the Name downtown Name point! early bird wine tasting special 11am-2pm today! were on water st.. across from BankD bank!??", "AutoID": "130822", "Date": "8/1/2015"}, {"MediaType": "twitter", "News": "y", "Year": "2015", "Month": "8", "FullText": "opening soon! new menu & revamped interior at Name Name BankA center! Name a# sneakpeak! INTERNET", "AutoID": "156096", "Date": "8/5/2015"}, {"MediaType": "facebook", "News": "n", "Year": "2015", "Month": "1", "FullText": "click here to support maret_twitin rodriguez jr Name Name by Name Name Name Name there every one this is a very hard situation for my family we are still lacking funds to continue with arrangements for are new angel Name Name Name you can donate here INTERNET or there is a memorial funding account at any BankA. account# 6380650371 we realy need the help and we greatly thank all of you that have helps us may Name blessed you all... https:// INTERNET = * number * & l = d113144cd5 INTERNET Name there we are asking for help to cover the funeral costs for maret_twitin rodriguez jr Name Name who was still young and had down sindrum are family is hurting and are very low on cash to help pay for are tradic loss it was unexspected... it happend christmas night and we are asking for help to give him a pr...", "AutoID": "92573", "Date": "1/5/2015"}, {"MediaType": "twitter", "News": "y", "Year": "2015", "Month": "8", "FullText": "ret_twit twit_hndl:# BankC sees$ Name trillion of potential stranded assets in# fossilfuel industry industry if# cop21 succeeds: shar. es/ 1vxra6# climate", "AutoID": "164783", "Date": "8/25/2015"}, {"MediaType": "twitter", "News": "y", "Year": "2015", "Month": "8", "FullText": "jnug BankD BankD & Name. ideas dlvr. it/ bzsflb$ jnug$ soxl$ Name$ dxcm# jnug# stocks# finance", "AutoID": "133130", "Date": "8/28/2015"}, {"MediaType": "facebook", "News": "y", "Year": "2014", "Month": "10", "FullText": "mayor Name Name joins BankA and neighbor Name to launch$ 5.2 Name for cincinnati# housing: INTERNET", "AutoID": "146048", "Date": "10/27/2014"}, {"MediaType": "facebook", "News": "y", "Year": "2014", "Month": "10", "FullText": "Name Name: the only ways to fix europe are fiscal union or a eurozone break-up BankD asset... Name Name: the only ways to fix europe are fiscal union or a eurozone break-up BankD asset management- stockport- financial advisers & wealth managers INTERNET", "AutoID": "116860", "Date": "10/13/2014"}, {"MediaType": "twitter", "News": "n", "Year": "2015", "Month": "8", "FullText": "twit_hndl yea they are both good banks. Name just saying BankA cause i work there lol", "AutoID": "51495", "Date": "8/27/2015"}, {"MediaType": "twitter", "News": "y", "Year": "2015", "Month": "8", "FullText": "while fossil reserves aren  t running out, our ability to burn them without limit may be... twit_hndl_BankC INTERNET ", "AutoID": "1572", "Date": "8/25/2015"}, {"MediaType": "twitter", "News": "n", "Year": "2015", "Month": "8", "FullText": "twit_hndl_BankC hello could you call me again immediately? since i think i got the wrong verification code", "AutoID": "9527", "Date": "8/25/2015"}, {"MediaType": "facebook", "News": "y", "Year": "2015", "Month": "1", "FullText": "bank robbery on Name Name BankA", "AutoID": "77693", "Date": "1/26/2015"}, {"MediaType": "twitter", "News": "n", "Year": "2015", "Month": "8", "FullText": "twit_hndl_BankA Name using my willpower, and my tweet, to try and win that BankB pack.# getcollegeready# contest", "AutoID": "48632", "Date": "8/6/2015"}, {"MediaType": "twitter", "News": "n", "Year": "2015", "Month": "8", "FullText": "my mom fills BankA envelopes with paper and drops it on the ground to trick people lol:/", "AutoID": "149776", "Date": "8/19/2015"}, {"MediaType": "facebook", "News": "n", "Year": "2015", "Month": "3", "FullText": "yall ever just lose it on someone when they something you consider patronizing when it come to your grieving? i went off on a guy via email today at BankA after he told me he understood how difficult life is since my husband passed away. now Name feeling a little bad because i was quite blunt in my reply. maybe today just isnt a people day for me.", "AutoID": "218639", "Date": "3/26/2015"}, {"MediaType": "facebook", "News": "n", "Year": "2014", "Month": "12", "FullText": "gonz  lez-r  os juan shared goldman sachs Name Name Name Name photo.# BankC   with Name Name.", "AutoID": "109055", "Date": "12/22/2014"}, {"MediaType": "facebook", "News": "n", "Year": "2014", "Month": "8", "FullText": "were next to BankD bank on water & wisconsin. come visit us!", "AutoID": "212531", "Date": "8/6/2014"}, {"MediaType": "twitter", "News": "n", "Year": "2015", "Month": "8", "FullText": "twit_hndl_BankA wonder how the vikes will do this year?# getcollegeready# contest", "AutoID": "50561", "Date": "8/6/2015"}, {"MediaType": "facebook", "News": "n", "Year": "2015", "Month": "6", "FullText": "i highly recommend going elsewhere for your banking needs. BankB had my mortgage application for 7 weeks before rejecting it yesterday over something they kneBankA rom day one. very unethical behavior. will be moving all of my business to banke.", "AutoID": "120191", "Date": "6/23/2015"}, {"MediaType": "twitter", "News": "n", "Year": "2015", "Month": "8", "FullText": "i had BankB 8 yrs ago. they debit my account b4 crediting deposits causing fees of refunded me but caused big problems INTERNET", "AutoID": "119180", "Date": "8/1/2015"}, {"MediaType": "twitter", "News": "y", "Year": "2015", "Month": "8", "FullText": "ret_twit twit_hndl: Name: verifone systemss Name overweight rating reaffirmed at BankD & Name.(pay )-...   dlvr. it/ bshvrf# privacy", "AutoID": "174958", "Date": "8/16/2015"}, {"MediaType": "twitter", "News": "n", "Year": "2015", "Month": "8", "FullText": "twit_hndl_BankD loved your post Name# miami so i shared it on my social feed! rbl. ms/ 1k1oyca", "AutoID": "28656", "Date": "8/17/2015"}, {"MediaType": "twitter", "News": "n", "Year": "2015", "Month": "8", "FullText": "how my card not work today, but was working friday night, smh# BankBproblems(BankB in atlanta, ga)INTERNET", "AutoID": "116191", "Date": "8/25/2015"}, {"MediaType": "twitter", "News": "n", "Year": "2015", "Month": "8", "FullText": "i remember i asked for$ 200 in ones from the teller at BankA she liked at my like Name for?? & i just said i gotta pay somebody bills", "AutoID": "122311", "Date": "8/18/2015"}, {"MediaType": "facebook", "News": "n", "Year": "2015", "Month": "6", "FullText": "with our partners at BankB this morning to cut the ribbon on a new space and celebrate some exBankCng# Name news!", "AutoID": "217084", "Date": "6/2/2015"}, {"MediaType": "twitter", "News": "n", "Year": "2015", "Month": "8", "FullText": "guys BankD is BankB  and thinks he is funny by creating fake account block twit_hndl and report him", "AutoID": "111305", "Date": "8/23/2015"}, {"MediaType": "twitter", "News": "n", "Year": "2015", "Month": "8", "FullText": "you can bank on BankD, baby!", "AutoID": "219364", "Date": "8/12/2015"}, {"MediaType": "twitter", "News": "y", "Year": "2015", "Month": "8", "FullText": "ret_twit twit_hndl: china will respond too late to avoid recession, BankC Name jmp. io/ s9rb", "AutoID": "169486", "Date": "8/28/2015"}, {"MediaType": "twitter", "News": "y", "Year": "2015", "Month": "8", "FullText": "BankBankC old agrees new deadline for charters towers funding Name Name Name INTERNET  via twit_hndl", "AutoID": "90813", "Date": "8/26/2015"}, {"MediaType": "twitter", "News": "n", "Year": "2015", "Month": "8", "FullText": "twit_hndl isnt it just now Name BankD me off Name your twitter account old lady old lady Name", "AutoID": "19753", "Date": "8/24/2015"}, {"MediaType": "twitter", "News": "n", "Year": "2015", "Month": "8", "FullText": "thou both BankB and BankC has approved me for a credit card Name always been scared", "AutoID": "197612", "Date": "8/13/2015"}, {"MediaType": "facebook", "News": "y", "Year": "2015", "Month": "1", "FullText": "BankD Name says big Name Name#BankD s Name says big Name Name- nasdaq# 757live INTERNET ", "AutoID": "132059", "Date": "1/15/2015"}, {"MediaType": "twitter", "News": "n", "Year": "2015", "Month": "8", "FullText": "seriously, twit_hndl_BankA, your customer service for business account holders is beyond atrocious- you should be ashamed- 90 min & counting", "AutoID": "182020", "Date": "8/16/2015"}, {"MediaType": "twitter", "News": "n", "Year": "2015", "Month": "8", "FullText": "i promise i wont ever flaunt my cash, i let BankA do that for me??", "AutoID": "122074", "Date": "8/13/2015"}, {"MediaType": "facebook", "News": "n", "Year": "2014", "Month": "10", "FullText": "the employees need a raise Name Name ceo at BankA!!!", "AutoID": "193642", "Date": "10/11/2014"}, {"MediaType": "twitter", "News": "n", "Year": "2015", "Month": "8", "FullText": "twit_hndl_BankB i am hereby boycotting everything to do with your company until your company defunds and denounces Name parenthood.", "AutoID": "11304", "Date": "8/1/2015"}, {"MediaType": "twitter", "News": "y", "Year": "2015", "Month": "8", "FullText": "Name Name  s neutral rating reiterated at BankC Name.$ boy ift. tt/ 1wgmtgh", "AutoID": "80791", "Date": "8/11/2015"}, {"MediaType": "twitter", "News": "y", "Year": "2015", "Month": "8", "FullText": "nascar# Name Name Name Name weekend BankB 500 charlotte motor speedway ebay. to/ 1gsizet# racing# tickets", "AutoID": "56335", "Date": "8/18/2015"}, {"MediaType": "twitter", "News": "n", "Year": "2015", "Month": "8", "FullText": "school starts soon and its expensive. fill our BankB packs.# getcollegeready# contest twit_hndl_BankA", "AutoID": "181016", "Date": "8/6/2015"}, {"MediaType": "facebook", "News": "n", "Year": "2015", "Month": "3", "FullText": "we are proud to announce BankA has returned as co-presenter of viet film fest film Name 2015! thank you BankA for your support over all these years in helping to shine light on vietnamese voices in cinema.", "AutoID": "205217", "Date": "3/14/2015"}, {"MediaType": "twitter", "News": "n", "Year": "2015", "Month": "8", "FullText": "ret_twit twit_hndl: Name time to go bigger than ever before! pennapps xii Name will take place at the BankA center center in philadelphia! INTERNET", "AutoID": "174695", "Date": "8/4/2015"}, {"MediaType": "twitter", "News": "n", "Year": "2015", "Month": "8", "FullText": "mr. arunjaitle f. Name, do you rememberpoll promises to Name BankCzens. most of income of sen BankC. comes from fixed deposits in nationised banks", "AutoID": "148874", "Date": "8/16/2015"}, {"MediaType": "facebook", "News": "n", "Year": "2015", "Month": "1", "FullText": "who has BankB!? lets Name Name Name b!", "AutoID": "215214", "Date": "1/13/2015"}, {"MediaType": "facebook", "News": "n", "Year": "2014", "Month": "9", "FullText": "got a BankB account. Name. hopefully get cali i. d. by tuesday if Name finbanke pulls through. Name. loving la:)", "AutoID": "110050", "Date": "9/12/2014"}, {"MediaType": "twitter", "News": "n", "Year": "2015", "Month": "8", "FullText": "and thats why i dont mess with twit_hndl_BankA", "AutoID": "67125", "Date": "8/10/2015"}, {"MediaType": "twitter", "News": "y", "Year": "2015", "Month": "8", "FullText": "ohsmallbz: BankD  Name BankD helps Name Name Name foundation power forward dlvr. it/ bxwh3w# cleveland", "AutoID": "154506", "Date": "8/24/2015"}, {"MediaType": "twitter", "News": "n", "Year": "2015", "Month": "8", "FullText": "twit_hndl BankB it is then", "AutoID": "33882", "Date": "8/8/2015"}, {"MediaType": "twitter", "News": "y", "Year": "2015", "Month": "8", "FullText": "BankD rates$ sune overweight on ability to tap$ 100s of billions in annual cash floBankA rom wind/ solar/ hydro INTERNET ", "AutoID": "137107", "Date": "8/31/2015"}, {"MediaType": "facebook", "News": "y", "Year": "2014", "Month": "8", "FullText": "BankB settles mortgage case Name$ 16.65 Name Name bank agreed to pay a record amount to the u. s. government to avoid prosecution for its fraudulent sale of toxic Name securities to investors in the lead-up to the financial crisis. INTERNET", "AutoID": "76234", "Date": "8/24/2014"}, {"MediaType": "twitter", "News": "y", "Year": "2015", "Month": "8", "FullText": "twit_hndl twit_hndl_BankD Name cares about a scam credit rating, when they downgraded the uss rating rating, knew that was a scam then, and got sued.", "AutoID": "23153", "Date": "8/25/2015"}, {"MediaType": "twitter", "News": "y", "Year": "2015", "Month": "8", "FullText": "xlf financials Name Name sector Name Name dlvr. it/ bydww6$ Name$ Name$ BankAc$ csco# Name# share# stocks", "AutoID": "218479", "Date": "8/26/2015"}, {"MediaType": "facebook", "News": "n", "Year": "2015", "Month": "5", "FullText": "happy to be banking with BankA again!... why did i ever leave!", "AutoID": "112013", "Date": "5/13/2015"}, {"MediaType": "twitter", "News": "n", "Year": "2015", "Month": "8", "FullText": "twit_hndl_BankA us trust is happy to have my business and is far more responsive than BankAb", "AutoID": "8737", "Date": "8/25/2015"}, {"MediaType": "facebook", "News": "y", "Year": "2015", "Month": "3", "FullText": "BankD  Name ceo Name Name once told Name Name to hit him with a fine because the bank could afford it BankD has a fortress balance sheet. INTERNET BankD ended up paying billions of dollars in fines.", "AutoID": "134116", "Date": "3/31/2015"}, {"MediaType": "facebook", "News": "n", "Year": "2014", "Month": "12", "FullText": "BankD mission main street Name BankDs$ 3 Name mission main street grants program program for small business is in full swing! apply or vote today! learn more here: INTERNET INTERNET", "AutoID": "87457", "Date": "12/13/2014"}, {"MediaType": "twitter", "News": "n", "Year": "2015", "Month": "8", "FullText": "you gotta love# friday at twit_hndl_BankB theres always a line.", "AutoID": "219519", "Date": "8/7/2015"}, {"MediaType": "twitter", "News": "n", "Year": "2015", "Month": "8", "FullText": "twit_hndl_BankA is always packed??", "AutoID": "48732", "Date": "8/17/2015"}, {"MediaType": "facebook", "News": "n", "Year": "2015", "Month": "5", "FullText": "BankA approved me for a secured credit card and i have had BankB for 7 years cant get one", "AutoID": "207313", "Date": "5/29/2015"}, {"MediaType": "facebook", "News": "y", "Year": "2014", "Month": "10", "FullText": "Name. Name s place plcs overweight rating reiterated at BankD & Name.. Name 924 Name. INTERNET$ Name# Name", "AutoID": "186789", "Date": "10/7/2014"}, {"MediaType": "facebook", "News": "n", "Year": "2014", "Month": "8", "FullText": "i would love to indulge in the purge... yes like the movie! sorry BankA  employees:-/", "AutoID": "124033", "Date": "8/11/2014"}, {"MediaType": "facebook", "News": "n", "Year": "2015", "Month": "4", "FullText": "Name now liberated from the shackles of fees BankB imposes on its checking account customers. over$ 100 was eaten out of my account in fees and i used my savings to pay off the subsequent overdraft. closed my savings and feel great. Name never bank with BankB as long as i have functioning frontal lobes.", "AutoID": "127681", "Date": "4/24/2015"}, {"MediaType": "facebook", "News": "n", "Year": "2015", "Month": "2", "FullText": "Name Name i have opened a bank account for Name Name at BankA for donations for his funeral fund. you can contact me for more information at 3524374771 or go to BankA and ask for your donation to be put in Name Name funeral fund account. thanks and god bless# pleasesharethispost", "AutoID": "146511", "Date": "2/10/2015"}, {"MediaType": "twitter", "News": "y", "Year": "2015", "Month": "8", "FullText": "former top army officer advisory position at BankD &# 038; Name. wpo. st/ w_ew0 generals at BankD  Name. time to nationalize", "AutoID": "105434", "Date": "8/20/2015"}, {"MediaType": "twitter", "News": "n", "Year": "2015", "Month": "8", "FullText": "for those of you who read my post yesterday about being ejected from the park adjacent to the BankB... fb. me/ 3hqwyprss", "AutoID": "105065", "Date": "8/10/2015"}, {"MediaType": "facebook", "News": "n", "Year": "2015", "Month": "1", "FullText": "just got home and it feels so weird. the turn up was real this past weekend according to BankA     lol. but i enjoyed every minute of it. next up..... Name Name for Name day. new Name i miss you", "AutoID": "138481", "Date": "1/20/2015"}, {"MediaType": "twitter", "News": "y", "Year": "2015", "Month": "8", "FullText": "goo. gl/ i9mi6g BankD BankD to move 2,150 jobs to new jersey from new Name- Name ow. ly/ 32gq2m", "AutoID": "109186", "Date": "8/5/2015"}, {"MediaType": "twitter", "News": "y", "Year": "2015", "Month": "8", "FullText": "ret_twit twit_hndl: morning 10: BankD private-banking settlement twit_hndl ceo to retire twit_hndl woos general electric INTERNET ", "AutoID": "164589", "Date": "8/19/2015"}, {"MediaType": "twitter", "News": "n", "Year": "2015", "Month": "8", "FullText": "cant thank twit_hndl twit_hndl twit_hndl & twit_hndl_BankB enough for this life changing opportunity! INTERNET", "AutoID": "84738", "Date": "8/19/2015"}, {"MediaType": "facebook", "News": "n", "Year": "2015", "Month": "1", "FullText": "Name-- april is correct. Name need to contact BankC directly to discuss any questions or concerns you may have regarding your Name card.", "AutoID": "132527", "Date": "1/6/2015"}, {"MediaType": "twitter", "News": "n", "Year": "2015", "Month": "8", "FullText": "twit_hndl twit_hndl_BankA twit_hndl_BankC twit_hndl thats amazing, great job! INTERNET", "AutoID": "6623", "Date": "8/5/2015"}, {"MediaType": "facebook", "News": "y", "Year": "2015", "Month": "4", "FullText": "BankD  Name said in february that greek banks collateral will run out by end of may# eBankC# greece INTERNET", "AutoID": "134888", "Date": "4/20/2015"}, {"MediaType": "twitter", "News": "y", "Year": "2015", "Month": "8", "FullText": "[ r-technology ] BankC: wind & solar energy Name better value than fossil fuels: lynk. pw/ 3hr5", "AutoID": "3024", "Date": "8/27/2015"}, {"MediaType": "twitter", "News": "y", "Year": "2015", "Month": "8", "FullText": "financial# update BankA advisers launch firm firm with dynasty financial Name- Name street journal ow. ly/ 33syye", "AutoID": "54471", "Date": "8/31/2015"}, {"MediaType": "facebook", "News": "n", "Year": "2015", "Month": "8", "FullText": "you re not going to want to miss tonight s finale of the Name Name park summer film Name. come join us for a special BankB  to the Name event and find out exactly what a gigawatt is!", "AutoID": "219879", "Date": "8/24/2015"}, {"MediaType": "facebook", "News": "y", "Year": "2014", "Month": "12", "FullText": "proofpoints buy rating rating reiterated at BankA & Name.. INTERNET$ pfpt# pfpt", "AutoID": "160151", "Date": "12/19/2014"}, {"MediaType": "facebook", "News": "n", "Year": "2015", "Month": "2", "FullText": "need a ski lift? transfer your BankD Name preferred points at full 1: 1 value to Name gold Name  to book your next ski getaway. visit INTERNET to redeem for all your travel needs.", "AutoID": "150702", "Date": "2/9/2015"}, {"MediaType": "twitter", "News": "n", "Year": "2015", "Month": "8", "FullText": "nepo5k2015 BankB riot damage# art# seattle INTERNET/", "AutoID": "56366", "Date": "8/30/2015"}, {"MediaType": "facebook", "News": "n", "Year": "2014", "Month": "10", "FullText": "BankD debit users- i had an issue today at the payless gas station station where using debit would only allow me to purBankD$ 1.00 worth of gas per transaction. the attendant said that it had been happening since yesterday and that you have to use credit for it to work properly. dont know hoBankA ar spread the issue is.", "AutoID": "87086", "Date": "10/18/2014"}, {"MediaType": "facebook", "News": "n", "Year": "2014", "Month": "10", "FullText": "dirty coast- BankD mission main street Name vote for dirty coast at https:// INTERNET- BankDs$ 3 Name mission main street Name program for small business is in full swing! apply or vote today! learn more here: INTERNET INTERNET", "AutoID": "97783", "Date": "10/17/2014"}, {"MediaType": "facebook", "News": "n", "Year": "2014", "Month": "11", "FullText": "please join us this week november 19th & 20th at our coffee clubs. Name Name with BankD  Name with be presenting guide to the markets.", "AutoID": "159035", "Date": "11/18/2014"}, {"MediaType": "twitter", "News": "n", "Year": "2015", "Month": "8", "FullText": "twit_hndl i ment BankB lol", "AutoID": "36773", "Date": "8/18/2015"}, {"MediaType": "twitter", "News": "n", "Year": "2015", "Month": "8", "FullText": "twit_hndl_BankB and that is why i recommend twit_hndl", "AutoID": "11134", "Date": "8/27/2015"}, {"MediaType": "twitter", "News": "y", "Year": "2015", "Month": "8", "FullText": "egypt c. bank approves Name, BankC deal bit. ly/ 1kmpkej# egypt twit_hndl", "AutoID": "54234", "Date": "8/26/2015"}, {"MediaType": "twitter", "News": "y", "Year": "2015", "Month": "8", "FullText": "Name receives Name rating from BankC Name.(ebay)INTERNET ", "AutoID": "100272", "Date": "8/9/2015"}, {"MediaType": "facebook", "News": "y", "Year": "2015", "Month": "3", "FullText": "BankC shares rise as bank passes stress tests INTERNET", "AutoID": "89654", "Date": "3/11/2015"}, {"MediaType": "twitter", "News": "n", "Year": "2015", "Month": "8", "FullText": "Name adjusts his hat, as he slowly approaches the busty twit_hndl. greeting her with that trademark grin. hey there BankB, been a while-", "AutoID": "64497", "Date": "8/8/2015"}, {"MediaType": "twitter", "News": "n", "Year": "2015", "Month": "8", "FullText": "ret_twit twit_hndl: congratulations to Name Name twit_hndl and Name Name at BankB on your upcoming Name Name! ow. ly/ r2ynh", "AutoID": "169941", "Date": "8/18/2015"}, {"MediaType": "facebook", "News": "y", "Year": "2015", "Month": "3", "FullText": "BankD bank has become the banke institution to face enforcement action in Name Name for breaches of the countrys anti-money laundering and counter financing of terrorism laws. the reserve bank of Name Name(rbnz)announced this morning that it had issued a formal warning to BankD bank for breaching the Name laundering and countering financing financing of terrorism act Name...", "AutoID": "136217", "Date": "3/8/2015"}, {"MediaType": "twitter", "News": "n", "Year": "2015", "Month": "8", "FullText": "BankD  Name: hold Name$ eursek 2 Name 9.40 call Name 9.60, p/ l-0.1 %", "AutoID": "135148", "Date": "8/6/2015"}, {"MediaType": "facebook", "News": "n", "Year": "2014", "Month": "12", "FullText": "add me on xboxlive robwhite87 made a new account.... Name advance BankA", "AutoID": "64682", "Date": "12/5/2014"}, {"MediaType": "facebook", "News": "n", "Year": "2014", "Month": "12", "FullText": "i told some trippy lady i needed money for weed and she looked at me and said you look like you got money for weed already. then other random people ask me for money walking down the street like i am a fucking BankB or something Name is wrong with that picture????????????????????????????????????????????????????????????????????????????????????????????????????????????? >", "AutoID": "122996", "Date": "12/15/2014"}, {"MediaType": "facebook", "News": "y", "Year": "2015", "Month": "4", "FullText": "u. s. banks join u. k. body on bank culture   Name Name s goldman? u. s. banks join u. k. body on bank culture   Name Name s goldman?: BankC Name. and Name... INTERNET# news# economy# Name INTERNET BankC Name. and Name Name have endorsed an effort to overhaul banker behavior in the u. k. by agreeing to have representatives on the new banking standards board. but the question remains: will Name Name group Name. sign up?", "AutoID": "201092", "Date": "4/2/2015"}, {"MediaType": "twitter", "News": "n", "Year": "2015", "Month": "8", "FullText": "hiring BankB looking for a west Name/ in Name Name, nv INTERNET/", "AutoID": "55362", "Date": "8/27/2015"}, {"MediaType": "twitter", "News": "y", "Year": "2015", "Month": "8", "FullText": "feds bust# suntrust,# BankA  and# Name bank employees in tax refund# scam bizj. us/ 1ix9yc$ Name$ BankAc$ Name  INTERNET", "AutoID": "103360", "Date": "8/21/2015"}, {"MediaType": "facebook", "News": "n", "Year": "2014", "Month": "12", "FullText": "trading standards would be where you go to BankD up something falsely advertised i believe.", "AutoID": "199807", "Date": "12/11/2014"}, {"MediaType": "facebook", "News": "n", "Year": "2014", "Month": "11", "FullText": "i just received the greatest news today. i got approved for a credit card from BankA!! soon Name be able to start up my credit in no time to get my first car!! Name always listens to my prayers.", "AutoID": "120603", "Date": "11/17/2014"}, {"MediaType": "facebook", "News": "n", "Year": "2015", "Month": "3", "FullText": "twit_hndl on instagram: today is my Name born# sons 7th# birthday mr. big bank BankD        ... today is my Name born# sons 7th# birthday mr. big bank BankD        # firstplacemosthandsomeface   https:// t. co/ 0ipuebxswn INTERNET ", "AutoID": "43613", "Date": "3/1/2015"}, {"MediaType": "twitter", "News": "y", "Year": "2015", "Month": "8", "FullText": "investingstockz: BankD, Name Name,# morganstanley to form data company: Name- ift. tt/ 1nwvspk;# forex# forextrading# fx", "AutoID": "129484", "Date": "8/20/2015"}, {"MediaType": "facebook", "News": "n", "Year": "2014", "Month": "10", "FullText": "Name about Name be late thanks Name BankA Name Name Name money from Name Name Name Name Name Name Name card decline Name the Name station & Name me thinking someone used Name debit card Name... but thankgod for Name banking Name i Name about Name have a fit!!!! anyway good morning:)", "AutoID": "127315", "Date": "10/15/2014"}, {"MediaType": "twitter", "News": "y", "Year": "2015", "Month": "8", "FullText": "ret_twit twit_hndl: Name Name Name well Name downgrade Name lowered estimates# apple# appleshares# BankB onforb. es/ 1ipdaff twit_hndl", "AutoID": "168884", "Date": "8/5/2015"}, {"MediaType": "facebook", "News": "n", "Year": "2014", "Month": "9", "FullText": "Name for BankB- day 1", "AutoID": "183014", "Date": "9/27/2014"}, {"MediaType": "twitter", "News": "y", "Year": "2015", "Month": "8", "FullText": "ret_twit twit_hndl: twit_hndl: twit_hndl twit_hndl twit_hndl_BankC leveraging# mobile technology to support# payments in the# philippines buff. ly/ 1kh0hrs", "AutoID": "171815", "Date": "8/2/2015"}, {"MediaType": "facebook", "News": "n", "Year": "2014", "Month": "12", "FullText": "Name Name shared goldman sachs Name Name Name Name photo.# BankC   with Name Name and giannis theodwridis Name. the real terrorists!", "AutoID": "182459", "Date": "12/29/2014"}, {"MediaType": "twitter", "News": "n", "Year": "2015", "Month": "8", "FullText": "ret_twit twit_hndl: thanks twit_hndl_BankA, twit_hndl, & twit_hndl for the financial & technical assistance to make this possible! twit_hndl INTERNET ", "AutoID": "174761", "Date": "8/7/2015"}, {"MediaType": "twitter", "News": "n", "Year": "2015", "Month": "8", "FullText": "the lady at BankA asked how to pronounce my middle name and said she had never heard it before. not the first time Name been told??", "AutoID": "194132", "Date": "8/24/2015"}, {"MediaType": "twitter", "News": "n", "Year": "2015", "Month": "8", "FullText": "twit_hndl i hope u dont have any BankD banks near your college", "AutoID": "33555", "Date": "8/19/2015"}, {"MediaType": "twitter", "News": "n", "Year": "2015", "Month": "8", "FullText": "twit_hndl_BankB_help what fuck i hit is bank my card is lock unlock my fuck card", "AutoID": "13052", "Date": "8/11/2015"}, {"MediaType": "twitter", "News": "n", "Year": "2015", "Month": "8", "FullText": "ret_twit twit_hndl: Name a move that a manager cant be afraid to make in a playoff BankD, thats why Name glad Name is here.", "AutoID": "166268", "Date": "8/7/2015"}, {"MediaType": "facebook", "News": "n", "Year": "2015", "Month": "2", "FullText": "no BankD or bank o f america yet still weak hackers.. lol", "AutoID": "152674", "Date": "2/16/2015"}, {"MediaType": "facebook", "News": "n", "Year": "2015", "Month": "2", "FullText": "hello if u have any active bank active bank account Name credit union union account and want to make$ 5000 quick and 100% % guaranteed send me a message or leave your name and number$$$$$$$ my brother works in BankD bank and can make a deposit into your account you can have$ 0 or a negative balance you can still make money$$$$$$ hit Name up seriouse people only anywhere in the u. s", "AutoID": "113220", "Date": "2/13/2015"}, {"MediaType": "facebook", "News": "n", "Year": "2014", "Month": "9", "FullText": "scf graphics Name- BankD mission main street Name vote for Name Name at https:// INTERNET- BankDs$ 3 Name mission main street Name program for small business is in full swing! apply or vote today! learn more here: INTERNET INTERNET", "AutoID": "180973", "Date": "9/20/2014"}, {"MediaType": "facebook", "News": "n", "Year": "2014", "Month": "9", "FullText": "opened my business account at BankA with Name Name for my new avon business. thank you sister < 3 if any of my new recruits need to open your just let me know and Name can help you out!!", "AutoID": "156047", "Date": "9/8/2014"}, {"MediaType": "facebook", "News": "n", "Year": "2014", "Month": "12", "FullText": "yo Name beyond mad Name livid yo i go to cash my check at the same bank i been going to for 16 weeks now she tell me she cant verify the company i work for rebanke BankA gets a life together", "AutoID": "219202", "Date": "12/13/2014"}, {"MediaType": "facebook", "News": "n", "Year": "2015", "Month": "1", "FullText": "which is better? BankA  Name BankC? pili na dali....", "AutoID": "214686", "Date": "1/26/2015"}, {"MediaType": "twitter", "News": "n", "Year": "2015", "Month": "8", "FullText": "i think i saw twit_hndl in the BankA parking lot. staring at the masi im staring at his porsche lol", "AutoID": "122816", "Date": "8/4/2015"}, {"MediaType": "facebook", "News": "y", "Year": "2015", "Month": "4", "FullText": "best & worst companies for Name and minorities reap sponsors twit_hndl & twit_hndl earn top ratings for diversity in hiring among companies in the s & p 100 INTERNET INTERNET a new ranking from calvert investments says BankC and Name have the best records on diversity in hiring. BankC and Name get top ratings...", "AutoID": "78958", "Date": "4/6/2015"}, {"MediaType": "facebook", "News": "y", "Year": "2014", "Month": "12", "FullText": "dr Name Name Name neutral rating reiterated at BankB.$ 75.00 Name. INTERNET$ Name# Name", "AutoID": "99594", "Date": "12/12/2014"}, {"MediaType": "twitter", "News": "n", "Year": "2015", "Month": "8", "FullText": "ret_twit twit_hndl: kendra lust lust is open for business# milf g0. BankA/ meet-her INTERNET", "AutoID": "168182", "Date": "8/18/2015"}, {"MediaType": "twitter", "News": "y", "Year": "2015", "Month": "8", "FullText": "ret_twit INTERNET  goo. gl/ 5kzf1v BankD: Name appears Name be breaking Name   INTERNET", "AutoID": "179731", "Date": "8/31/2015"}, {"MediaType": "facebook", "News": "y", "Year": "2014", "Month": "11", "FullText": "dish Name Name Name raised by BankC Name. to$ 94.00. buy rating. INTERNET$ dish# dish", "AutoID": "97888", "Date": "11/21/2014"}, {"MediaType": "twitter", "News": "y", "Year": "2015", "Month": "8", "FullText": "ret_twit twit_hndl: twit_hndl_BankA makes a point that people w/ written business plans have a higher % of success. INTERNET", "AutoID": "173895", "Date": "8/1/2015"}, {"MediaType": "twitter", "News": "n", "Year": "2015", "Month": "8", "FullText": "ret_twit twit_hndl: twit_hndl you letting niggas play with your money BankB??", "AutoID": "163793", "Date": "8/4/2015"}, {"MediaType": "facebook", "News": "n", "Year": "2014", "Month": "8", "FullText": "i love thursday.... i got that BankB app.. yo check has Name deposit turnt up. might hit the after hours tonite", "AutoID": "121414", "Date": "8/29/2014"}, {"MediaType": "twitter", "News": "y", "Year": "2015", "Month": "8", "FullText": "excerpts from Name Name criticism of BankBs# corpgov decisions: yhoo. it/ 1mdrcie via twit_hndl", "AutoID": "102270", "Date": "8/22/2015"}, {"MediaType": "twitter", "News": "y", "Year": "2015", "Month": "8", "FullText": "cornerstone makes two senior hires: cornerstone has poached top BankD  morgan BankD  Name real estate manager... bit. ly/ 1tp2ea8# property# Name", "AutoID": "94446", "Date": "8/17/2015"}, {"MediaType": "facebook", "News": "y", "Year": "2014", "Month": "8", "FullText": "countrywide acquisition Name Name BankB BankB has been ordered to pay nearly$ 1.3 billion in penalties stemming from a countrywide program nicknamed the hustle. INTERNET", "AutoID": "94684", "Date": "8/8/2014"}, {"MediaType": "twitter", "News": "n", "Year": "2015", "Month": "8", "FullText": "twit_hndl_BankA wont stop trying# getcollegeready# contest", "AutoID": "50560", "Date": "8/6/2015"}, {"MediaType": "facebook", "News": "y", "Year": "2015", "Month": "2", "FullText": "kaiser aluminum corp. Name Name. s Name cut by BankD & Name. to$ 76.00. neutral rating. INTERNET$ Name# Name", "AutoID": "139263", "Date": "2/19/2015"}, {"MediaType": "twitter", "News": "n", "Year": "2015", "Month": "8", "FullText": "BankD  BankD  BankD stock quote: INTERNET. INTERNET", "AutoID": "135323", "Date": "8/17/2015"}, {"MediaType": "twitter", "News": "n", "Year": "2015", "Month": "8", "FullText": "twit_hndl_BankB_help... atm doesnt credit deposited checks after depositing cash in same transaction. will video my next atm deposit.", "AutoID": "13082", "Date": "8/14/2015"}, {"MediaType": "twitter", "News": "n", "Year": "2015", "Month": "8", "FullText": "in BankB with grandma its full ppl are even outside woah: 0 big line", "AutoID": "128340", "Date": "8/1/2015"}, {"MediaType": "twitter", "News": "n", "Year": "2015", "Month": "8", "FullText": "we tracked this account down on a wild BankD that led us to a very strange social media website(pt. 2)twit_hndl twit_hndl twit_hndl", "AutoID": "205839", "Date": "8/17/2015"}, {"MediaType": "twitter", "News": "y", "Year": "2015", "Month": "8", "FullText": "former BankD  Name analyst in Name Name pleads not guilty to insider... fb. me/ fynplwbg", "AutoID": "105376", "Date": "8/26/2015"}, {"MediaType": "facebook", "News": "n", "Year": "2015", "Month": "6", "FullText": "welcome to the Name family Name. how do you like the Name so far?- BankD c. community manager", "AutoID": "206298", "Date": "6/10/2015"}, {"MediaType": "facebook", "News": "n", "Year": "2015", "Month": "3", "FullText": "toastmasters educational speech- the visionary leader first educational speech done! thanks for connected speakers at BankB Name Name for hosting me.", "AutoID": "198599", "Date": "3/30/2015"}, {"MediaType": "facebook", "News": "n", "Year": "2014", "Month": "11", "FullText": "oh yall must dont know we been doin this# 44# freebands# juug shit shit# BankD# usaa# navyfederal# suntrust# BankA # BankB pick Name bank Name been striking", "AutoID": "154453", "Date": "11/18/2014"}, {"MediaType": "facebook", "News": "n", "Year": "2014", "Month": "8", "FullText": "BankA has free online banking and free debit card...", "AutoID": "208750", "Date": "8/14/2014"}, {"MediaType": "twitter", "News": "y", "Year": "2015", "Month": "8", "FullText": "imago galleries artist Name artist Name h. Name is announced as one of the masters in 2015 united states states BankD bank master... fb. me/ 4pwd1lorx", "AutoID": "128134", "Date": "8/13/2015"}, {"MediaType": "twitter", "News": "y", "Year": "2015", "Month": "8", "FullText": "$ BankB interesting october stock options for BankB: interesting october stock options for bank of Name... onforb. es/ 1tmzf6p", "AutoID": "59257", "Date": "8/18/2015"}, {"MediaType": "facebook", "News": "n", "Year": "2014", "Month": "8", "FullText": "free Name BankC!!!!! no remorse$$$$$ Name money and tuff BankC BankC responding to some Name contest beef...... shot and edited by dizzydott(Name Name)", "AutoID": "105977", "Date": "8/5/2014"}, {"MediaType": "twitter", "News": "n", "Year": "2015", "Month": "8", "FullText": "zennie62: i liked a Name video from zennie62 youtu. be/ 4pbtn6tbf8m? a Name use BankB atm at Name Name INTERNET", "AutoID": "220251", "Date": "8/29/2015"}, {"MediaType": "twitter", "News": "n", "Year": "2015", "Month": "8", "FullText": "i like BankB packs. i like prizes. gimme, gimme, gimme! twit_hndl_BankA. you know u wanna!: )# getcollegeready# contest", "AutoID": "120965", "Date": "8/6/2015"}, {"MediaType": "facebook", "News": "n", "Year": "2014", "Month": "11", "FullText": "fuck up morning but it ok through cause i am going to see usher tomorrow night at the BankA center", "AutoID": "106650", "Date": "11/10/2014"}, {"MediaType": "twitter", "News": "n", "Year": "2015", "Month": "8", "FullText": "BankA said bankers bank Name mama said niggas beg, my name climbing?? the ranks??- twit_hndl in the mix", "AutoID": "2406", "Date": "8/17/2015"}, {"MediaType": "facebook", "News": "n", "Year": "2014", "Month": "10", "FullText": "if you were at my 50th or lcf music music in the park you will remember them. they will be playing this saturday at 5:30 at the montrose oktoberfest on the BankC bank stage. get there early.", "AutoID": "126617", "Date": "10/2/2014"}, {"MediaType": "twitter", "News": "n", "Year": "2015", "Month": "8", "FullText": "twit_hndl_BankB_help ridiculous Name. branch in mesa, az. 6 customers in line. 1 teller. 3 personal bankers sitting at desks doing nothing.", "AutoID": "13043", "Date": "8/22/2015"}, {"MediaType": "twitter", "News": "y", "Year": "2015", "Month": "8", "FullText": "ontheway# repost INTERNET cation  dont BankD Name BankD after trading for  INTERNET ", "AutoID": "56818", "Date": "8/14/2015"}, {"MediaType": "twitter", "News": "n", "Year": "2015", "Month": "8", "FullText": "twit_hndl_BankA dinner break break!!# getcollegeready# contest", "AutoID": "47553", "Date": "8/6/2015"}, {"MediaType": "twitter", "News": "n", "Year": "2015", "Month": "8", "FullText": "twit_hndl ill meet u at BankB__", "AutoID": "24696", "Date": "8/11/2015"}, {"MediaType": "twitter", "News": "n", "Year": "2015", "Month": "8", "FullText": "application# development Name- Name president: BankD, solent. INTERNET ", "AutoID": "69054", "Date": "8/18/2015"}, {"MediaType": "twitter", "News": "n", "Year": "2015", "Month": "8", "FullText": "i got the BankB app on my phone and every time i look at it i giggle cause its abbreviated to BankB. BankB deez nuts", "AutoID": "119014", "Date": "8/25/2015"}, {"MediaType": "facebook", "News": "n", "Year": "2015", "Month": "6", "FullText": "the sun is shining and the golfers are in full swing at our golf Name presented by BankA!# BankAgolfclassic", "AutoID": "195046", "Date": "6/22/2015"}, {"MediaType": "twitter", "News": "y", "Year": "2015", "Month": "8", "FullText": "financenews BankD BankD loosens grip on jumbo mortgages- BankD & Name. wednesday said it is relaxing i... ow. ly/ 32hriy", "AutoID": "54458", "Date": "8/6/2015"}, {"MediaType": "facebook", "News": "n", "Year": "2014", "Month": "10", "FullText": "craboo tree- BankD mission main street Name vote for craboo tree tree at https:// INTERNET- BankDs$ 3 Name mission main street Name program for small business is in full swing! apply or vote today! learn more here: INTERNET INTERNET", "AutoID": "94777", "Date": "10/9/2014"}, {"MediaType": "facebook", "News": "y", "Year": "2015", "Month": "1", "FullText": "BankC sees net income plunge as Name legal costs soar to$ 2.9 bn INTERNET INTERNET bank saw a dramatic rise in legal costs as net income fell by 86 %", "AutoID": "91849", "Date": "1/16/2015"}, {"MediaType": "twitter", "News": "n", "Year": "2015", "Month": "8", "FullText": "getcollegeready# contest twit_hndl_BankA??????????????????????", "AutoID": "54847", "Date": "8/6/2015"}, {"MediaType": "twitter", "News": "n", "Year": "2015", "Month": "8", "FullText": "some around-the-world fun at the twit_hndl_BankC kids clinic with twit_hndl & twit_hndl# BankCopen INTERNET", "AutoID": "185493", "Date": "8/3/2015"}, {"MediaType": "twitter", "News": "n", "Year": "2015", "Month": "8", "FullText": "twit_hndl_BankD Name give the option of making a pymt to a BankD customer via a debit card card from a nonBankD bank.", "AutoID": "17305", "Date": "8/11/2015"}, {"MediaType": "twitter", "News": "y", "Year": "2015", "Month": "8", "FullText": "step 3 in financial college planning-- > review your loan options [ video ]# paid# BankA  INTERNET ", "AutoID": "187326", "Date": "8/16/2015"}, {"MediaType": "twitter", "News": "n", "Year": "2015", "Month": "8", "FullText": "BankB is??, they always messing up my stuff", "AutoID": "74524", "Date": "8/6/2015"}, {"MediaType": "twitter", "News": "y", "Year": "2015", "Month": "8", "FullText": "providence Name BankB Name. shareholders will get the chance to vote on whether the lenders board s... ow. ly/ 329dor", "AutoID": "160290", "Date": "8/3/2015"}, {"MediaType": "facebook", "News": "n", "Year": "2015", "Month": "2", "FullText": "fleetwood mac mac tickets for$ 200 or more? get used to it Name sucks dmreg. co Name performers this year demand higher-priced tickets for BankA Name concerts", "AutoID": "104563", "Date": "2/11/2015"}, {"MediaType": "twitter", "News": "n", "Year": "2015", "Month": "8", "FullText": "zen and the art of BankB Name", "AutoID": "220241", "Date": "8/3/2015"}, {"MediaType": "facebook", "News": "n", "Year": "2014", "Month": "9", "FullText": "our BankD  team grabing the runners up.... Name tournament...........", "AutoID": "156595", "Date": "9/22/2014"}, {"MediaType": "facebook", "News": "n", "Year": "2014", "Month": "12", "FullText": "dean Name shared Name Name Name Name Name photo.# goldmansachs# BankD# wallstreet# finance# banksters# financialterrorists# economics# money# classwarfare# morganstanley# usbank# BankB# hsbc# Name# federalreserve# BankA # BankC# BankC   with Name Name.", "AutoID": "96454", "Date": "12/18/2014"}, {"MediaType": "facebook", "News": "n", "Year": "2014", "Month": "9", "FullText": "freddys one stop shopping.. said BankD bank bank... archer moon not BankD", "AutoID": "105844", "Date": "9/22/2014"}, {"MediaType": "twitter", "News": "n", "Year": "2015", "Month": "8", "FullText": "good# markets chat happening today on twit_hndl radio at 3:45 pm et w/ darrell cronk Name from twit_hndl_BankA,# BankAii", "AutoID": "109315", "Date": "8/10/2015"}, {"MediaType": "facebook", "News": "n", "Year": "2015", "Month": "2", "FullText": "BankA & Name stage coach 20 long including front handle 9 1/ 2 tall 8 wide all wood 25.00 located in mineola cross posted", "AutoID": "206731", "Date": "2/25/2015"}, {"MediaType": "twitter", "News": "n", "Year": "2015", "Month": "8", "FullText": "rip to my twit_hndl_BankB savings account. 2004 2015. gone but never forgotten????", "AutoID": "163014", "Date": "8/28/2015"}, {"MediaType": "twitter", "News": "y", "Year": "2015", "Month": "8", "FullText": "ret_twit twit_hndl:# banks under Name.# banking# fintech# startups# BankA # BankC# BankB via twit_hndl INTERNET ", "AutoID": "173490", "Date": "8/5/2015"}, {"MediaType": "twitter", "News": "y", "Year": "2015", "Month": "8", "FullText": "$ BankD - general ray Name senior advisor to BankD & Name. INTERNET ", "AutoID": "60000", "Date": "8/20/2015"}, {"MediaType": "twitter", "News": "y", "Year": "2015", "Month": "8", "FullText": "blackjack# fresh# photobooth# soccer insider secrets Name secrets of boat buying: 20 year veteran who brokered Name Name Name over 1,400 BankB bit. ly/ 1inuogq", "AutoID": "53070", "Date": "8/28/2015"}, {"MediaType": "facebook", "News": "n", "Year": "2014", "Month": "8", "FullText": "trade my 100k fresh us leads to BankB Name", "AutoID": "199718", "Date": "8/16/2014"}, {"MediaType": "twitter", "News": "n", "Year": "2015", "Month": "8", "FullText": "thank you BankA for fucking my day even more up??", "AutoID": "191259", "Date": "8/10/2015"}, {"MediaType": "twitter", "News": "y", "Year": "2015", "Month": "8", "FullText": "today Name: BankB Name Name Name fed bit. ly/ 1iowsbb", "AutoID": "198625", "Date": "8/5/2015"}, {"MediaType": "twitter", "News": "y", "Year": "2015", "Month": "8", "FullText": "ret_twit twit_hndl:# bbcnews# Name# Name# ret_twite Name Name of kent * lord# windsor# BankD# Name criminal prosecution case sco. lt/ 5tr6ff", "AutoID": "166789", "Date": "8/9/2015"}, {"MediaType": "twitter", "News": "n", "Year": "2015", "Month": "8", "FullText": "BankA college BankB pack contest contest.# getcollegeready# contest", "AutoID": "208015", "Date": "8/6/2015"}, {"MediaType": "twitter", "News": "y", "Year": "2015", "Month": "8", "FullText": "Name Name Name hold rating reiterated at BankD & Name..$ 52.00 Name. ift. tt/ 1kduadn$ kors# kors", "AutoID": "146913", "Date": "8/10/2015"}, {"MediaType": "twitter", "News": "n", "Year": "2015", "Month": "8", "FullText": "twit_hndl_BankA i been on hold for 15mns noBankA am, everybody off today or.......?", "AutoID": "7475", "Date": "8/25/2015"}, {"MediaType": "facebook", "News": "n", "Year": "2015", "Month": "2", "FullText": "has a check for$ 185 but cant cash it tomorrow because i dont have a ride to BankA. damn this kinda sucks.", "AutoID": "112127", "Date": "2/14/2015"}, {"MediaType": "twitter", "News": "y", "Year": "2015", "Month": "8", "FullText": "ret_twit twit_hndl: twit_hndl is this kicked out from a whistleblower lawsuit? does covington represent BankD? INTERNET  INTERNET", "AutoID": "173213", "Date": "8/26/2015"}, {"MediaType": "twitter", "News": "n", "Year": "2015", "Month": "8", "FullText": "Name. my mistake for giving twit_hndl_BankB_help props. just looked at my account and i was charged$ 20 for the card & to have it rushed! i did not ask", "AutoID": "133081", "Date": "8/21/2015"}, {"MediaType": "twitter", "News": "y", "Year": "2015", "Month": "8", "FullText": "Name business Name Name Name to$ 87.00(Name ): stock analysts at BankD & Name. raised  goo. gl/ fb/ 6xnu3w", "AutoID": "160332", "Date": "8/15/2015"}, {"MediaType": "twitter", "News": "n", "Year": "2015", "Month": "8", "FullText": "why would BankD need this guy! INTERNET ", "AutoID": "216501", "Date": "8/26/2015"}, {"MediaType": "twitter", "News": "n", "Year": "2015", "Month": "8", "FullText": "dang used to live on that aesthetic and another running the whole bankrobber aesthetic before or after they picked up BankD as a sponser?", "AutoID": "95863", "Date": "8/18/2015"}, {"MediaType": "twitter", "News": "n", "Year": "2015", "Month": "8", "FullText": "twit_hndl_BankC twit_hndl Name my homage 2 Name. wait 4 it... youtu. be/ c-nxacdnhfe# fanlife# sweepstakes", "AutoID": "18591", "Date": "8/10/2015"}, {"MediaType": "facebook", "News": "n", "Year": "2014", "Month": "11", "FullText": "how you try and play me out me on facebook and everyone you know Name riding me like Name case/ BankA and BankC bank all in one", "AutoID": "116416", "Date": "11/14/2014"}, {"MediaType": "facebook", "News": "n", "Year": "2015", "Month": "7", "FullText": "Name annoyed. south state state bank has bought all BankB branches in south Name and georgia and customers like myself dont have a choice. if i wanted to be apart of south state i would have. i chose BankB for the reason that they have multiple branches in different states. but no now Name being forced to deal with a company i dont want. i guess Name be going BankB  to usaa and beginning with BankA. i dont have time for this foolishness. thank you BankB for thinking of your south Name customers. we are aware of how you truly feel.", "AutoID": "127348", "Date": "7/8/2015"}, {"MediaType": "twitter", "News": "y", "Year": "2015", "Month": "8", "FullText": "ret_twit twit_hndl:# fanniegate# fhfa$ fnma BankA hires key aid Name Name Name calls Name  reform  at Name Name/ freddie mac mac INTERNET ", "AutoID": "174788", "Date": "8/10/2015"}, {"MediaType": "facebook", "News": "n", "Year": "2015", "Month": "4", "FullText": "i love Name cardinals shared st. louis. Name Name photo. unleash the clydesdales. opening week is here. celebrate the new season by sharing your favorite cardinals memory with BankB using# mlbmemorybank.", "AutoID": "121371", "Date": "4/9/2015"}, {"MediaType": "twitter", "News": "n", "Year": "2015", "Month": "8", "FullText": "bank of italy was the original name of BankB.", "AutoID": "77630", "Date": "8/28/2015"}, {"MediaType": "facebook", "News": "y", "Year": "2014", "Month": "12", "FullText": "BankD embraces shareholder friendly corporate culture BankD embraces shareholder friendly corporate culture# alpha# beta# article INTERNET ", "AutoID": "136291", "Date": "12/25/2014"}, {"MediaType": "facebook", "News": "n", "Year": "2014", "Month": "11", "FullText": "apparently no one wanted to go to work at BankB today. i cant log into my account and i cant get a phone call to go through. trying to pay bills and hard to do that if i cant monitor my account.", "AutoID": "68866", "Date": "11/3/2014"}, {"MediaType": "twitter", "News": "y", "Year": "2015", "Month": "8", "FullText": "BankA Name to be front-runner to buy Name Name unit- Name dlvr. it/ bzpfjw", "AutoID": "210723", "Date": "8/28/2015"}, {"MediaType": "twitter", "News": "y", "Year": "2015", "Month": "8", "FullText": "pvh corp pt lowered Name Name Name to$ 126.00 at BankD & Name.$ Name ift. tt/ 1jlyeum", "AutoID": "160540", "Date": "8/27/2015"}]